{"trajectory": [{"time": 9.2934e-05, "gear": 1, "engineOn": 1, "direction": 1, "manualIntervention": 0, "speed": 0.0, "acc": 0.0, "brake": 0.0, "isLaneChanging": 0, "isOverTaking": 0, "isTurningAround": 0, "currentLanenumber": -1, "currentLanedirection": 0, "speedLimitlowerLimit": 0, "speedLimitupperLimit": 1000, "honkingAllowed": 1, "crosswalkAhead": 200, "junctionAhead": 200, "stopSignAhead": 200, "signalAhead": 0, "stoplineAhead": 200, "streetLightOn": 0, "specialLocationAheadlocation": 0, "specialLocationAheadtype": 0, "trafficLightAheadcolor": 3, "trafficLightAheadblink": 0, "PriorityNPCAhead": 0, "PriorityPedsAhead": 0, "isTrafficJam": 0, "reach_destination": 1, "collision": 0, "NPCAheadAhead": 1000, "NPCAheadspeed": 0, "NearestNPCAhead": 129.03625012694005, "NearestNPCspeed": 0.0, "NPCOppositeAhead": 1000, "NPCOppositespeed": 0}, {"time": 8.0244e-05, "gear": 1, "engineOn": 1, "direction": 1, "manualIntervention": 0, "speed": 0.0, "acc": 0.0, "brake": 0.0, "isLaneChanging": 0, "isOverTaking": 0, "isTurningAround": 0, "currentLanenumber": -1, "currentLanedirection": 0, "speedLimitlowerLimit": 0, "speedLimitupperLimit": 1000, "honkingAllowed": 1, "crosswalkAhead": 200, "junctionAhead": 200, "stopSignAhead": 200, "signalAhead": 0, "stoplineAhead": 200, "streetLightOn": 0, "specialLocationAheadlocation": 0, "specialLocationAheadtype": 0, "trafficLightAheadcolor": 3, "trafficLightAheadblink": 0, "PriorityNPCAhead": 0, "PriorityPedsAhead": 0, "isTrafficJam": 0, "reach_destination": 1, "collision": 0, "NPCAheadAhead": 1000, "NPCAheadspeed": 0, "NearestNPCAhead": 129.03625012694005, "NearestNPCspeed": 0.0, "NPCOppositeAhead": 1000, "NPCOppositespeed": 0}, {"time": 0.0, "gear": 1, "engineOn": 1, "direction": 1, "manualIntervention": 0, "speed": 0.0, "acc": 0.0, "brake": 0.0, "isLaneChanging": 0, "isOverTaking": 0, "isTurningAround": 0, "currentLanenumber": -1, "currentLanedirection": 0, "speedLimitlowerLimit": 0, "speedLimitupperLimit": 1000, "honkingAllowed": 1, "crosswalkAhead": 200, "junctionAhead": 200, "stopSignAhead": 200, "signalAhead": 0, "stoplineAhead": 200, "streetLightOn": 0, "specialLocationAheadlocation": 0, "specialLocationAheadtype": 0, "trafficLightAheadcolor": 3, "trafficLightAheadblink": 0, "PriorityNPCAhead": 0, "PriorityPedsAhead": 0, "isTrafficJam": 0, "reach_destination": 1, "collision": 0, "NPCAheadAhead": 1000, "NPCAheadspeed": 0, "NearestNPCAhead": 129.03625012694005, "NearestNPCspeed": 0.0, "NPCOppositeAhead": 1000, "NPCOppositespeed": 0}, {"time": 6.8865e-05, "gear": 1, "engineOn": 1, "direction": 1, "manualIntervention": 0, "speed": 0.0, "acc": 0.0, "brake": 0.0, "isLaneChanging": 0, "isOverTaking": 0, "isTurningAround": 0, "currentLanenumber": -1, "currentLanedirection": 0, "speedLimitlowerLimit": 0, "speedLimitupperLimit": 1000, "honkingAllowed": 1, "crosswalkAhead": 200, "junctionAhead": 200, "stopSignAhead": 200, "signalAhead": 0, "stoplineAhead": 200, "streetLightOn": 0, "specialLocationAheadlocation": 0, "specialLocationAheadtype": 0, "trafficLightAheadcolor": 3, "trafficLightAheadblink": 0, "PriorityNPCAhead": 0, "PriorityPedsAhead": 0, "isTrafficJam": 0, "reach_destination": 1, "collision": 0, "NPCAheadAhead": 1000, "NPCAheadspeed": 0, "NearestNPCAhead": 129.03625012694005, "NearestNPCspeed": 0.0, "NPCOppositeAhead": 1000, "NPCOppositespeed": 0}, {"time": 5.8104e-05, "gear": 1, "engineOn": 1, "direction": 1, "manualIntervention": 0, "speed": 0.0, "acc": 0.0, "brake": 0.0, "isLaneChanging": 0, "isOverTaking": 0, "isTurningAround": 0, "currentLanenumber": -1, "currentLanedirection": 0, "speedLimitlowerLimit": 0, "speedLimitupperLimit": 1000, "honkingAllowed": 1, "crosswalkAhead": 200, "junctionAhead": 200, "stopSignAhead": 200, "signalAhead": 0, "stoplineAhead": 200, "streetLightOn": 0, "specialLocationAheadlocation": 0, "specialLocationAheadtype": 0, "trafficLightAheadcolor": 3, "trafficLightAheadblink": 0, "PriorityNPCAhead": 0, "PriorityPedsAhead": 0, "isTrafficJam": 0, "reach_destination": 1, "collision": 0, "NPCAheadAhead": 1000, "NPCAheadspeed": 0, "NearestNPCAhead": 129.03625012694005, "NearestNPCspeed": 0.0, "NPCOppositeAhead": 1000, "NPCOppositespeed": 0}, {"time": 7.2904e-05, "gear": 1, "engineOn": 1, "direction": 1, "manualIntervention": 0, "speed": 0.0, "acc": 0.0, "brake": 0.0, "isLaneChanging": 0, "isOverTaking": 0, "isTurningAround": 0, "currentLanenumber": -1, "currentLanedirection": 0, "speedLimitlowerLimit": 0, "speedLimitupperLimit": 1000, "honkingAllowed": 1, "crosswalkAhead": 200, "junctionAhead": 200, "stopSignAhead": 200, "signalAhead": 0, "stoplineAhead": 200, "streetLightOn": 0, "specialLocationAheadlocation": 0, "specialLocationAheadtype": 0, "trafficLightAheadcolor": 3, "trafficLightAheadblink": 0, "PriorityNPCAhead": 0, "PriorityPedsAhead": 0, "isTrafficJam": 0, "reach_destination": 1, "collision": 0, "NPCAheadAhead": 1000, "NPCAheadspeed": 0, "NearestNPCAhead": 129.03625012694005, "NearestNPCspeed": 0.0, "NPCOppositeAhead": 1000, "NPCOppositespeed": 0}, {"time": 8.542e-05, "gear": 1, "engineOn": 1, "direction": 1, "manualIntervention": 0, "speed": 0.0, "acc": 0.0, "brake": 0.0, "isLaneChanging": 0, "isOverTaking": 0, "isTurningAround": 0, "currentLanenumber": -1, "currentLanedirection": 0, "speedLimitlowerLimit": 0, "speedLimitupperLimit": 1000, "honkingAllowed": 1, "crosswalkAhead": 200, "junctionAhead": 200, "stopSignAhead": 200, "signalAhead": 0, "stoplineAhead": 200, "streetLightOn": 0, "specialLocationAheadlocation": 0, "specialLocationAheadtype": 0, "trafficLightAheadcolor": 3, "trafficLightAheadblink": 0, "PriorityNPCAhead": 0, "PriorityPedsAhead": 0, "isTrafficJam": 0, "reach_destination": 1, "collision": 0, "NPCAheadAhead": 1000, "NPCAheadspeed": 0, "NearestNPCAhead": 129.03625012694005, "NearestNPCspeed": 0.0, "NPCOppositeAhead": 1000, "NPCOppositespeed": 0}, {"time": 7.6892e-05, "gear": 1, "engineOn": 1, "direction": 1, "manualIntervention": 0, "speed": 0.0, "acc": 0.0, "brake": 0.0, "isLaneChanging": 0, "isOverTaking": 0, "isTurningAround": 0, "currentLanenumber": -1, "currentLanedirection": 0, "speedLimitlowerLimit": 0, "speedLimitupperLimit": 1000, "honkingAllowed": 1, "crosswalkAhead": 200, "junctionAhead": 200, "stopSignAhead": 200, "signalAhead": 0, "stoplineAhead": 200, "streetLightOn": 0, "specialLocationAheadlocation": 0, "specialLocationAheadtype": 0, "trafficLightAheadcolor": 3, "trafficLightAheadblink": 0, "PriorityNPCAhead": 0, "PriorityPedsAhead": 0, "isTrafficJam": 0, "reach_destination": 1, "collision": 0, "NPCAheadAhead": 1000, "NPCAheadspeed": 0, "NearestNPCAhead": 129.03625012694005, "NearestNPCspeed": 0.0, "NPCOppositeAhead": 1000, "NPCOppositespeed": 0}, {"time": 9.9269e-05, "gear": 1, "engineOn": 1, "direction": 1, "manualIntervention": 0, "speed": 0.0, "acc": 0.0, "brake": 0.0, "isLaneChanging": 0, "isOverTaking": 0, "isTurningAround": 0, "currentLanenumber": -1, "currentLanedirection": 0, "speedLimitlowerLimit": 0, "speedLimitupperLimit": 1000, "honkingAllowed": 1, "crosswalkAhead": 200, "junctionAhead": 200, "stopSignAhead": 200, "signalAhead": 0, "stoplineAhead": 200, "streetLightOn": 0, "specialLocationAheadlocation": 0, "specialLocationAheadtype": 0, "trafficLightAheadcolor": 3, "trafficLightAheadblink": 0, "PriorityNPCAhead": 0, "PriorityPedsAhead": 0, "isTrafficJam": 0, "reach_destination": 1, "collision": 0, "NPCAheadAhead": 1000, "NPCAheadspeed": 0, "NearestNPCAhead": 129.03625012694005, "NearestNPCspeed": 0.0, "NPCOppositeAhead": 1000, "NPCOppositespeed": 0}, {"time": 9.6047e-05, "gear": 1, "engineOn": 1, "direction": 1, "manualIntervention": 0, "speed": 0.0, "acc": 0.0, "brake": 0.0, "isLaneChanging": 0, "isOverTaking": 0, "isTurningAround": 0, "currentLanenumber": -1, "currentLanedirection": 0, "speedLimitlowerLimit": 0, "speedLimitupperLimit": 1000, "honkingAllowed": 1, "crosswalkAhead": 200, "junctionAhead": 200, "stopSignAhead": 200, "signalAhead": 0, "stoplineAhead": 200, "streetLightOn": 0, "specialLocationAheadlocation": 0, "specialLocationAheadtype": 0, "trafficLightAheadcolor": 3, "trafficLightAheadblink": 0, "PriorityNPCAhead": 0, "PriorityPedsAhead": 0, "isTrafficJam": 0, "reach_destination": 1, "collision": 0, "NPCAheadAhead": 1000, "NPCAheadspeed": 0, "NearestNPCAhead": 129.03625012694005, "NearestNPCspeed": 0.0, "NPCOppositeAhead": 1000, "NPCOppositespeed": 0}, {"time": 0.019497705, "gear": 1, "engineOn": 1, "direction": 1, "manualIntervention": 0, "speed": 0.0, "acc": 0.0, "brake": 0.0, "isLaneChanging": 0, "isOverTaking": 0, "isTurningAround": 0, "currentLanenumber": -1, "currentLanedirection": 0, "speedLimitlowerLimit": 0, "speedLimitupperLimit": 1000, "honkingAllowed": 1, "crosswalkAhead": 200, "junctionAhead": 200, "stopSignAhead": 200, "signalAhead": 0, "stoplineAhead": 200, "streetLightOn": 0, "specialLocationAheadlocation": 0, "specialLocationAheadtype": 0, "trafficLightAheadcolor": 3, "trafficLightAheadblink": 0, "PriorityNPCAhead": 0, "PriorityPedsAhead": 0, "isTrafficJam": 0, "reach_destination": 1, "collision": 0, "NPCAheadAhead": 1000, "NPCAheadspeed": 0, "NearestNPCAhead": 129.03625012694005, "NearestNPCspeed": 0.0, "NPCOppositeAhead": 1000, "NPCOppositespeed": 0}, {"time": 0.039579317, "gear": 1, "engineOn": 1, "direction": 1, "manualIntervention": 0, "speed": 0.0, "acc": 0.0, "brake": 0.0, "isLaneChanging": 0, "isOverTaking": 0, "isTurningAround": 0, "currentLanenumber": -1, "currentLanedirection": 0, "speedLimitlowerLimit": 0, "speedLimitupperLimit": 1000, "honkingAllowed": 1, "crosswalkAhead": 200, "junctionAhead": 200, "stopSignAhead": 200, "signalAhead": 0, "stoplineAhead": 200, "streetLightOn": 0, "specialLocationAheadlocation": 0, "specialLocationAheadtype": 0, "trafficLightAheadcolor": 3, "trafficLightAheadblink": 0, "PriorityNPCAhead": 0, "PriorityPedsAhead": 0, "isTrafficJam": 0, "reach_destination": 1, "collision": 0, "NPCAheadAhead": 1000, "NPCAheadspeed": 0, "NearestNPCAhead": 129.03625012694005, "NearestNPCspeed": 0.0, "NPCOppositeAhead": 1000, "NPCOppositespeed": 0}, {"time": 0.009541125, "gear": 1, "engineOn": 1, "direction": 1, "manualIntervention": 0, "speed": 0.0, "acc": 0.0, "brake": 0.0, "isLaneChanging": 0, "isOverTaking": 0, "isTurningAround": 0, "currentLanenumber": -1, "currentLanedirection": 0, "speedLimitlowerLimit": 0, "speedLimitupperLimit": 1000, "honkingAllowed": 1, "crosswalkAhead": 200, "junctionAhead": 200, "stopSignAhead": 200, "signalAhead": 0, "stoplineAhead": 200, "streetLightOn": 0, "specialLocationAheadlocation": 0, "specialLocationAheadtype": 0, "trafficLightAheadcolor": 3, "trafficLightAheadblink": 0, "PriorityNPCAhead": 0, "PriorityPedsAhead": 0, "isTrafficJam": 0, "reach_destination": 1, "collision": 0, "NPCAheadAhead": 1000, "NPCAheadspeed": 0, "NearestNPCAhead": 129.03625012694005, "NearestNPCspeed": 0.0, "NPCOppositeAhead": 1000, "NPCOppositespeed": 0}, {"time": 0.029534383, "gear": 1, "engineOn": 1, "direction": 1, "manualIntervention": 0, "speed": 0.0, "acc": 0.0, "brake": 0.0, "isLaneChanging": 0, "isOverTaking": 0, "isTurningAround": 0, "currentLanenumber": -1, "currentLanedirection": 0, "speedLimitlowerLimit": 0, "speedLimitupperLimit": 1000, "honkingAllowed": 1, "crosswalkAhead": 200, "junctionAhead": 200, "stopSignAhead": 200, "signalAhead": 0, "stoplineAhead": 200, "streetLightOn": 0, "specialLocationAheadlocation": 0, "specialLocationAheadtype": 0, "trafficLightAheadcolor": 3, "trafficLightAheadblink": 0, "PriorityNPCAhead": 0, "PriorityPedsAhead": 0, "isTrafficJam": 0, "reach_destination": 1, "collision": 0, "NPCAheadAhead": 1000, "NPCAheadspeed": 0, "NearestNPCAhead": 129.03625012694005, "NearestNPCspeed": 0.0, "NPCOppositeAhead": 1000, "NPCOppositespeed": 0}, {"time": 0.049671636, "gear": 1, "engineOn": 1, "direction": 1, "manualIntervention": 0, "speed": 0.0, "acc": 0.0, "brake": 0.0, "isLaneChanging": 0, "isOverTaking": 0, "isTurningAround": 0, "currentLanenumber": -1, "currentLanedirection": 0, "speedLimitlowerLimit": 0, "speedLimitupperLimit": 1000, "honkingAllowed": 1, "crosswalkAhead": 200, "junctionAhead": 200, "stopSignAhead": 200, "signalAhead": 0, "stoplineAhead": 200, "streetLightOn": 0, "specialLocationAheadlocation": 0, "specialLocationAheadtype": 0, "trafficLightAheadcolor": 3, "trafficLightAheadblink": 0, "PriorityNPCAhead": 0, "PriorityPedsAhead": 0, "isTrafficJam": 0, "reach_destination": 1, "collision": 0, "NPCAheadAhead": 1000, "NPCAheadspeed": 0, "NearestNPCAhead": 129.0362505060784, "NearestNPCspeed": 0.0, "NPCOppositeAhead": 1000, "NPCOppositespeed": 0}, {"time": 0.059689264, "gear": 1, "engineOn": 1, "direction": 1, "manualIntervention": 0, "speed": 0.0, "acc": 0.0, "brake": 0.0, "isLaneChanging": 0, "isOverTaking": 0, "isTurningAround": 0, "currentLanenumber": -1, "currentLanedirection": 0, "speedLimitlowerLimit": 0, "speedLimitupperLimit": 1000, "honkingAllowed": 1, "crosswalkAhead": 200, "junctionAhead": 200, "stopSignAhead": 200, "signalAhead": 0, "stoplineAhead": 200, "streetLightOn": 0, "specialLocationAheadlocation": 0, "specialLocationAheadtype": 0, "trafficLightAheadcolor": 3, "trafficLightAheadblink": 0, "PriorityNPCAhead": 0, "PriorityPedsAhead": 0, "isTrafficJam": 0, "reach_destination": 1, "collision": 0, "NPCAheadAhead": 1000, "NPCAheadspeed": 0, "NearestNPCAhead": 129.0362505060784, "NearestNPCspeed": 0.0, "NPCOppositeAhead": 1000, "NPCOppositespeed": 0}, {"time": 0.069549247, "gear": 1, "engineOn": 1, "direction": 1, "manualIntervention": 0, "speed": 0.0, "acc": 0.0, "brake": 0.0, "isLaneChanging": 0, "isOverTaking": 0, "isTurningAround": 0, "currentLanenumber": -1, "currentLanedirection": 0, "speedLimitlowerLimit": 0, "speedLimitupperLimit": 1000, "honkingAllowed": 1, "crosswalkAhead": 200, "junctionAhead": 200, "stopSignAhead": 200, "signalAhead": 0, "stoplineAhead": 200, "streetLightOn": 0, "specialLocationAheadlocation": 0, "specialLocationAheadtype": 0, "trafficLightAheadcolor": 3, "trafficLightAheadblink": 0, "PriorityNPCAhead": 0, "PriorityPedsAhead": 0, "isTrafficJam": 0, "reach_destination": 1, "collision": 0, "NPCAheadAhead": 1000, "NPCAheadspeed": 0, "NearestNPCAhead": 129.0362505060784, "NearestNPCspeed": 0.0, "NPCOppositeAhead": 1000, "NPCOppositespeed": 0}, {"time": 0.089597424, "gear": 1, "engineOn": 1, "direction": 1, "manualIntervention": 0, "speed": 0.0, "acc": 0.0, "brake": 0.0, "isLaneChanging": 0, "isOverTaking": 0, "isTurningAround": 0, "currentLanenumber": -1, "currentLanedirection": 0, "speedLimitlowerLimit": 0, "speedLimitupperLimit": 1000, "honkingAllowed": 1, "crosswalkAhead": 200, "junctionAhead": 200, "stopSignAhead": 200, "signalAhead": 0, "stoplineAhead": 200, "streetLightOn": 0, "specialLocationAheadlocation": 0, "specialLocationAheadtype": 0, "trafficLightAheadcolor": 3, "trafficLightAheadblink": 0, "PriorityNPCAhead": 0, "PriorityPedsAhead": 0, "isTrafficJam": 0, "reach_destination": 1, "collision": 0, "NPCAheadAhead": 1000, "NPCAheadspeed": 0, "NearestNPCAhead": 129.0362505060784, "NearestNPCspeed": 0.0, "NPCOppositeAhead": 1000, "NPCOppositespeed": 0}, {"time": 0.079540027, "gear": 1, "engineOn": 1, "direction": 1, "manualIntervention": 0, "speed": 0.0, "acc": 0.0, "brake": 0.0, "isLaneChanging": 0, "isOverTaking": 0, "isTurningAround": 0, "currentLanenumber": -1, "currentLanedirection": 0, "speedLimitlowerLimit": 0, "speedLimitupperLimit": 1000, "honkingAllowed": 1, "crosswalkAhead": 200, "junctionAhead": 200, "stopSignAhead": 200, "signalAhead": 0, "stoplineAhead": 200, "streetLightOn": 0, "specialLocationAheadlocation": 0, "specialLocationAheadtype": 0, "trafficLightAheadcolor": 3, "trafficLightAheadblink": 0, "PriorityNPCAhead": 0, "PriorityPedsAhead": 0, "isTrafficJam": 0, "reach_destination": 1, "collision": 0, "NPCAheadAhead": 1000, "NPCAheadspeed": 0, "NearestNPCAhead": 129.0362505060784, "NearestNPCspeed": 0.0, "NPCOppositeAhead": 1000, "NPCOppositespeed": 0}, {"time": 0.099552147, "gear": 1, "engineOn": 1, "direction": 1, "manualIntervention": 0, "speed": 0.0, "acc": 0.0, "brake": 0.0, "isLaneChanging": 0, "isOverTaking": 0, "isTurningAround": 0, "currentLanenumber": -1, "currentLanedirection": 0, "speedLimitlowerLimit": 0, "speedLimitupperLimit": 1000, "honkingAllowed": 1, "crosswalkAhead": 200, "junctionAhead": 200, "stopSignAhead": 200, "signalAhead": 0, "stoplineAhead": 200, "streetLightOn": 0, "specialLocationAheadlocation": 0, "specialLocationAheadtype": 0, "trafficLightAheadcolor": 3, "trafficLightAheadblink": 0, "PriorityNPCAhead": 0, "PriorityPedsAhead": 0, "isTrafficJam": 0, "reach_destination": 1, "collision": 0, "NPCAheadAhead": 1000, "NPCAheadspeed": 0, "NearestNPCAhead": 129.0362505060784, "NearestNPCspeed": 0.0, "NPCOppositeAhead": 1000, "NPCOppositespeed": 0}, {"time": 0.139554021, "gear": 1, "engineOn": 1, "direction": 1, "manualIntervention": 0, "speed": 0.0, "acc": 0.0, "brake": 0.0, "isLaneChanging": 0, "isOverTaking": 0, "isTurningAround": 0, "currentLanenumber": -1, "currentLanedirection": 0, "speedLimitlowerLimit": 0, "speedLimitupperLimit": 1000, "honkingAllowed": 1, "crosswalkAhead": 200, "junctionAhead": 200, "stopSignAhead": 200, "signalAhead": 0, "stoplineAhead": 200, "streetLightOn": 0, "specialLocationAheadlocation": 0, "specialLocationAheadtype": 0, "trafficLightAheadcolor": 3, "trafficLightAheadblink": 0, "PriorityNPCAhead": 0, "PriorityPedsAhead": 0, "isTrafficJam": 0, "reach_destination": 1, "collision": 0, "NPCAheadAhead": 1000, "NPCAheadspeed": 0, "NearestNPCAhead": 129.0362505060784, "NearestNPCspeed": 0.0, "NPCOppositeAhead": 1000, "NPCOppositespeed": 0}, {"time": 0.119511007, "gear": 1, "engineOn": 1, "direction": 1, "manualIntervention": 0, "speed": 0.0, "acc": 0.0, "brake": 0.0, "isLaneChanging": 0, "isOverTaking": 0, "isTurningAround": 0, "currentLanenumber": -1, "currentLanedirection": 0, "speedLimitlowerLimit": 0, "speedLimitupperLimit": 1000, "honkingAllowed": 1, "crosswalkAhead": 200, "junctionAhead": 200, "stopSignAhead": 200, "signalAhead": 0, "stoplineAhead": 200, "streetLightOn": 0, "specialLocationAheadlocation": 0, "specialLocationAheadtype": 0, "trafficLightAheadcolor": 3, "trafficLightAheadblink": 0, "PriorityNPCAhead": 0, "PriorityPedsAhead": 0, "isTrafficJam": 0, "reach_destination": 1, "collision": 0, "NPCAheadAhead": 1000, "NPCAheadspeed": 0, "NearestNPCAhead": 129.0362505060784, "NearestNPCspeed": 0.0, "NPCOppositeAhead": 1000, "NPCOppositespeed": 0}, {"time": 0.179644619, "gear": 1, "engineOn": 1, "direction": 1, "manualIntervention": 0, "speed": 0.0, "acc": 0.0, "brake": 0.0, "isLaneChanging": 0, "isOverTaking": 0, "isTurningAround": 0, "currentLanenumber": -1, "currentLanedirection": 0, "speedLimitlowerLimit": 0, "speedLimitupperLimit": 1000, "honkingAllowed": 1, "crosswalkAhead": 200, "junctionAhead": 200, "stopSignAhead": 200, "signalAhead": 0, "stoplineAhead": 200, "streetLightOn": 0, "specialLocationAheadlocation": 0, "specialLocationAheadtype": 0, "trafficLightAheadcolor": 3, "trafficLightAheadblink": 0, "PriorityNPCAhead": 0, "PriorityPedsAhead": 0, "isTrafficJam": 0, "reach_destination": 1, "collision": 0, "NPCAheadAhead": 1000, "NPCAheadspeed": 0, "NearestNPCAhead": 129.03625075264975, "NearestNPCspeed": 0.0, "NPCOppositeAhead": 1000, "NPCOppositespeed": 0}, {"time": 0.109505843, "gear": 1, "engineOn": 1, "direction": 1, "manualIntervention": 0, "speed": 0.0, "acc": 0.0, "brake": 0.0, "isLaneChanging": 0, "isOverTaking": 0, "isTurningAround": 0, "currentLanenumber": -1, "currentLanedirection": 0, "speedLimitlowerLimit": 0, "speedLimitupperLimit": 1000, "honkingAllowed": 1, "crosswalkAhead": 200, "junctionAhead": 200, "stopSignAhead": 200, "signalAhead": 0, "stoplineAhead": 200, "streetLightOn": 0, "specialLocationAheadlocation": 0, "specialLocationAheadtype": 0, "trafficLightAheadcolor": 3, "trafficLightAheadblink": 0, "PriorityNPCAhead": 0, "PriorityPedsAhead": 0, "isTrafficJam": 0, "reach_destination": 1, "collision": 0, "NPCAheadAhead": 1000, "NPCAheadspeed": 0, "NearestNPCAhead": 129.0362505060784, "NearestNPCspeed": 0.0, "NPCOppositeAhead": 1000, "NPCOppositespeed": 0}, {"time": 0.149563642, "gear": 1, "engineOn": 1, "direction": 1, "manualIntervention": 0, "speed": 0.0, "acc": 0.0, "brake": 0.0, "isLaneChanging": 0, "isOverTaking": 0, "isTurningAround": 0, "currentLanenumber": -1, "currentLanedirection": 0, "speedLimitlowerLimit": 0, "speedLimitupperLimit": 1000, "honkingAllowed": 1, "crosswalkAhead": 200, "junctionAhead": 200, "stopSignAhead": 200, "signalAhead": 0, "stoplineAhead": 200, "streetLightOn": 0, "specialLocationAheadlocation": 0, "specialLocationAheadtype": 0, "trafficLightAheadcolor": 3, "trafficLightAheadblink": 0, "PriorityNPCAhead": 0, "PriorityPedsAhead": 0, "isTrafficJam": 0, "reach_destination": 1, "collision": 0, "NPCAheadAhead": 1000, "NPCAheadspeed": 0, "NearestNPCAhead": 129.03625075264975, "NearestNPCspeed": 0.0, "NPCOppositeAhead": 1000, "NPCOppositespeed": 0}, {"time": 0.129492763, "gear": 1, "engineOn": 1, "direction": 1, "manualIntervention": 0, "speed": 0.0, "acc": 0.0, "brake": 0.0, "isLaneChanging": 0, "isOverTaking": 0, "isTurningAround": 0, "currentLanenumber": -1, "currentLanedirection": 0, "speedLimitlowerLimit": 0, "speedLimitupperLimit": 1000, "honkingAllowed": 1, "crosswalkAhead": 200, "junctionAhead": 200, "stopSignAhead": 200, "signalAhead": 0, "stoplineAhead": 200, "streetLightOn": 0, "specialLocationAheadlocation": 0, "specialLocationAheadtype": 0, "trafficLightAheadcolor": 3, "trafficLightAheadblink": 0, "PriorityNPCAhead": 0, "PriorityPedsAhead": 0, "isTrafficJam": 0, "reach_destination": 1, "collision": 0, "NPCAheadAhead": 1000, "NPCAheadspeed": 0, "NearestNPCAhead": 129.0362505060784, "NearestNPCspeed": 0.0, "NPCOppositeAhead": 1000, "NPCOppositespeed": 0}, {"time": 0.169648516, "gear": 1, "engineOn": 1, "direction": 1, "manualIntervention": 0, "speed": 0.0, "acc": 0.0, "brake": 0.0, "isLaneChanging": 0, "isOverTaking": 0, "isTurningAround": 0, "currentLanenumber": -1, "currentLanedirection": 0, "speedLimitlowerLimit": 0, "speedLimitupperLimit": 1000, "honkingAllowed": 1, "crosswalkAhead": 200, "junctionAhead": 200, "stopSignAhead": 200, "signalAhead": 0, "stoplineAhead": 200, "streetLightOn": 0, "specialLocationAheadlocation": 0, "specialLocationAheadtype": 0, "trafficLightAheadcolor": 3, "trafficLightAheadblink": 0, "PriorityNPCAhead": 0, "PriorityPedsAhead": 0, "isTrafficJam": 0, "reach_destination": 1, "collision": 0, "NPCAheadAhead": 1000, "NPCAheadspeed": 0, "NearestNPCAhead": 129.03625075264975, "NearestNPCspeed": 0.0, "NPCOppositeAhead": 1000, "NPCOppositespeed": 0}, {"time": 0.1595229, "gear": 1, "engineOn": 1, "direction": 1, "manualIntervention": 0, "speed": 0.0, "acc": 0.0, "brake": 0.0, "isLaneChanging": 0, "isOverTaking": 0, "isTurningAround": 0, "currentLanenumber": -1, "currentLanedirection": 0, "speedLimitlowerLimit": 0, "speedLimitupperLimit": 1000, "honkingAllowed": 1, "crosswalkAhead": 200, "junctionAhead": 200, "stopSignAhead": 200, "signalAhead": 0, "stoplineAhead": 200, "streetLightOn": 0, "specialLocationAheadlocation": 0, "specialLocationAheadtype": 0, "trafficLightAheadcolor": 3, "trafficLightAheadblink": 0, "PriorityNPCAhead": 0, "PriorityPedsAhead": 0, "isTrafficJam": 0, "reach_destination": 1, "collision": 0, "NPCAheadAhead": 1000, "NPCAheadspeed": 0, "NearestNPCAhead": 129.03625075264975, "NearestNPCspeed": 0.0, "NPCOppositeAhead": 1000, "NPCOppositespeed": 0}, {"time": 0.189594875, "gear": 1, "engineOn": 1, "direction": 1, "manualIntervention": 0, "speed": 0.0, "acc": 0.0, "brake": 0.0, "isLaneChanging": 0, "isOverTaking": 0, "isTurningAround": 0, "currentLanenumber": -1, "currentLanedirection": 0, "speedLimitlowerLimit": 0, "speedLimitupperLimit": 1000, "honkingAllowed": 1, "crosswalkAhead": 200, "junctionAhead": 200, "stopSignAhead": 200, "signalAhead": 0, "stoplineAhead": 200, "streetLightOn": 0, "specialLocationAheadlocation": 0, "specialLocationAheadtype": 0, "trafficLightAheadcolor": 3, "trafficLightAheadblink": 0, "PriorityNPCAhead": 0, "PriorityPedsAhead": 0, "isTrafficJam": 0, "reach_destination": 1, "collision": 0, "NPCAheadAhead": 1000, "NPCAheadspeed": 0, "NearestNPCAhead": 129.03625075264975, "NearestNPCspeed": 0.0, "NPCOppositeAhead": 1000, "NPCOppositespeed": 0}, {"time": 0.199537726, "gear": 1, "engineOn": 1, "direction": 1, "manualIntervention": 0, "speed": 0.0, "acc": 0.0, "brake": 0.0, "isLaneChanging": 0, "isOverTaking": 0, "isTurningAround": 0, "currentLanenumber": -1, "currentLanedirection": 0, "speedLimitlowerLimit": 0, "speedLimitupperLimit": 1000, "honkingAllowed": 1, "crosswalkAhead": 200, "junctionAhead": 200, "stopSignAhead": 200, "signalAhead": 0, "stoplineAhead": 200, "streetLightOn": 0, "specialLocationAheadlocation": 0, "specialLocationAheadtype": 0, "trafficLightAheadcolor": 3, "trafficLightAheadblink": 0, "PriorityNPCAhead": 0, "PriorityPedsAhead": 0, "isTrafficJam": 0, "reach_destination": 1, "collision": 0, "NPCAheadAhead": 1000, "NPCAheadspeed": 0, "NearestNPCAhead": 129.03625075264975, "NearestNPCspeed": 0.0, "NPCOppositeAhead": 1000, "NPCOppositespeed": 0}, {"time": 0.219574889, "gear": 1, "engineOn": 1, "direction": 1, "manualIntervention": 0, "speed": 0.0, "acc": 0.0, "brake": 0.0, "isLaneChanging": 0, "isOverTaking": 0, "isTurningAround": 0, "currentLanenumber": -1, "currentLanedirection": 0, "speedLimitlowerLimit": 0, "speedLimitupperLimit": 1000, "honkingAllowed": 1, "crosswalkAhead": 200, "junctionAhead": 200, "stopSignAhead": 200, "signalAhead": 0, "stoplineAhead": 200, "streetLightOn": 0, "specialLocationAheadlocation": 0, "specialLocationAheadtype": 0, "trafficLightAheadcolor": 3, "trafficLightAheadblink": 0, "PriorityNPCAhead": 0, "PriorityPedsAhead": 0, "isTrafficJam": 0, "reach_destination": 1, "collision": 0, "NPCAheadAhead": 1000, "NPCAheadspeed": 0, "NearestNPCAhead": 129.03625075264975, "NearestNPCspeed": 0.0, "NPCOppositeAhead": 1000, "NPCOppositespeed": 0}, {"time": 0.249282266, "gear": 1, "engineOn": 1, "direction": 1, "manualIntervention": 0, "speed": 0.0, "acc": 0.0, "brake": 0.0, "isLaneChanging": 0, "isOverTaking": 0, "isTurningAround": 0, "currentLanenumber": -1, "currentLanedirection": 0, "speedLimitlowerLimit": 0, "speedLimitupperLimit": 1000, "honkingAllowed": 1, "crosswalkAhead": 200, "junctionAhead": 200, "stopSignAhead": 200, "signalAhead": 0, "stoplineAhead": 200, "streetLightOn": 0, "specialLocationAheadlocation": 0, "specialLocationAheadtype": 0, "trafficLightAheadcolor": 3, "trafficLightAheadblink": 0, "PriorityNPCAhead": 0, "PriorityPedsAhead": 0, "isTrafficJam": 0, "reach_destination": 1, "collision": 0, "NPCAheadAhead": 1000, "NPCAheadspeed": 0, "NearestNPCAhead": 129.03625099914413, "NearestNPCspeed": 0.0, "NPCOppositeAhead": 1000, "NPCOppositespeed": 0}, {"time": 0.209542569, "gear": 1, "engineOn": 1, "direction": 1, "manualIntervention": 0, "speed": 0.0, "acc": 0.0, "brake": 0.0, "isLaneChanging": 0, "isOverTaking": 0, "isTurningAround": 0, "currentLanenumber": -1, "currentLanedirection": 0, "speedLimitlowerLimit": 0, "speedLimitupperLimit": 1000, "honkingAllowed": 1, "crosswalkAhead": 200, "junctionAhead": 200, "stopSignAhead": 200, "signalAhead": 0, "stoplineAhead": 200, "streetLightOn": 0, "specialLocationAheadlocation": 0, "specialLocationAheadtype": 0, "trafficLightAheadcolor": 3, "trafficLightAheadblink": 0, "PriorityNPCAhead": 0, "PriorityPedsAhead": 0, "isTrafficJam": 0, "reach_destination": 1, "collision": 0, "NPCAheadAhead": 1000, "NPCAheadspeed": 0, "NearestNPCAhead": 129.03625075264975, "NearestNPCspeed": 0.0, "NPCOppositeAhead": 1000, "NPCOppositespeed": 0}, {"time": 0.242650688, "gear": 1, "engineOn": 1, "direction": 1, "manualIntervention": 0, "speed": 0.0, "acc": 0.0, "brake": 0.0, "isLaneChanging": 0, "isOverTaking": 0, "isTurningAround": 0, "currentLanenumber": -1, "currentLanedirection": 0, "speedLimitlowerLimit": 0, "speedLimitupperLimit": 1000, "honkingAllowed": 1, "crosswalkAhead": 200, "junctionAhead": 200, "stopSignAhead": 200, "signalAhead": 0, "stoplineAhead": 200, "streetLightOn": 0, "specialLocationAheadlocation": 0, "specialLocationAheadtype": 0, "trafficLightAheadcolor": 3, "trafficLightAheadblink": 0, "PriorityNPCAhead": 0, "PriorityPedsAhead": 0, "isTrafficJam": 0, "reach_destination": 1, "collision": 0, "NPCAheadAhead": 1000, "NPCAheadspeed": 0, "NearestNPCAhead": 129.03625075264975, "NearestNPCspeed": 0.0, "NPCOppositeAhead": 1000, "NPCOppositespeed": 0}, {"time": 0.240800149, "gear": 1, "engineOn": 1, "direction": 1, "manualIntervention": 0, "speed": 0.0, "acc": 0.0, "brake": 0.0, "isLaneChanging": 0, "isOverTaking": 0, "isTurningAround": 0, "currentLanenumber": -1, "currentLanedirection": 0, "speedLimitlowerLimit": 0, "speedLimitupperLimit": 1000, "honkingAllowed": 1, "crosswalkAhead": 200, "junctionAhead": 200, "stopSignAhead": 200, "signalAhead": 0, "stoplineAhead": 200, "streetLightOn": 0, "specialLocationAheadlocation": 0, "specialLocationAheadtype": 0, "trafficLightAheadcolor": 3, "trafficLightAheadblink": 0, "PriorityNPCAhead": 0, "PriorityPedsAhead": 0, "isTrafficJam": 0, "reach_destination": 1, "collision": 0, "NPCAheadAhead": 1000, "NPCAheadspeed": 0, "NearestNPCAhead": 129.03625075264975, "NearestNPCspeed": 0.0, "NPCOppositeAhead": 1000, "NPCOppositespeed": 0}, {"time": 0.258759111, "gear": 1, "engineOn": 1, "direction": 1, "manualIntervention": 0, "speed": 0.0, "acc": 0.0, "brake": 0.0, "isLaneChanging": 0, "isOverTaking": 0, "isTurningAround": 0, "currentLanenumber": -1, "currentLanedirection": 0, "speedLimitlowerLimit": 0, "speedLimitupperLimit": 1000, "honkingAllowed": 1, "crosswalkAhead": 200, "junctionAhead": 200, "stopSignAhead": 200, "signalAhead": 0, "stoplineAhead": 200, "streetLightOn": 0, "specialLocationAheadlocation": 0, "specialLocationAheadtype": 0, "trafficLightAheadcolor": 3, "trafficLightAheadblink": 0, "PriorityNPCAhead": 0, "PriorityPedsAhead": 0, "isTrafficJam": 0, "reach_destination": 1, "collision": 0, "NPCAheadAhead": 1000, "NPCAheadspeed": 0, "NearestNPCAhead": 129.03625099914413, "NearestNPCspeed": 0.0, "NPCOppositeAhead": 1000, "NPCOppositespeed": 0}, {"time": 0.268762777, "gear": 1, "engineOn": 1, "direction": 1, "manualIntervention": 0, "speed": 0.0, "acc": 0.0, "brake": 0.0, "isLaneChanging": 0, "isOverTaking": 0, "isTurningAround": 0, "currentLanenumber": -1, "currentLanedirection": 0, "speedLimitlowerLimit": 0, "speedLimitupperLimit": 1000, "honkingAllowed": 1, "crosswalkAhead": 200, "junctionAhead": 200, "stopSignAhead": 200, "signalAhead": 0, "stoplineAhead": 200, "streetLightOn": 0, "specialLocationAheadlocation": 0, "specialLocationAheadtype": 0, "trafficLightAheadcolor": 3, "trafficLightAheadblink": 0, "PriorityNPCAhead": 0, "PriorityPedsAhead": 0, "isTrafficJam": 0, "reach_destination": 1, "collision": 0, "NPCAheadAhead": 1000, "NPCAheadspeed": 0, "NearestNPCAhead": 129.03625099914413, "NearestNPCspeed": 0.0, "NPCOppositeAhead": 1000, "NPCOppositespeed": 0}, {"time": 0.278729105, "gear": 1, "engineOn": 1, "direction": 1, "manualIntervention": 0, "speed": 0.0, "acc": 0.0, "brake": 0.0, "isLaneChanging": 0, "isOverTaking": 0, "isTurningAround": 0, "currentLanenumber": -1, "currentLanedirection": 0, "speedLimitlowerLimit": 0, "speedLimitupperLimit": 1000, "honkingAllowed": 1, "crosswalkAhead": 200, "junctionAhead": 200, "stopSignAhead": 200, "signalAhead": 0, "stoplineAhead": 200, "streetLightOn": 0, "specialLocationAheadlocation": 0, "specialLocationAheadtype": 0, "trafficLightAheadcolor": 3, "trafficLightAheadblink": 0, "PriorityNPCAhead": 0, "PriorityPedsAhead": 0, "isTrafficJam": 0, "reach_destination": 1, "collision": 0, "NPCAheadAhead": 1000, "NPCAheadspeed": 0, "NearestNPCAhead": 129.03625099914413, "NearestNPCspeed": 0.0, "NPCOppositeAhead": 1000, "NPCOppositespeed": 0}, {"time": 0.298618474, "gear": 1, "engineOn": 1, "direction": 1, "manualIntervention": 0, "speed": 0.0, "acc": 0.0, "brake": 0.0, "isLaneChanging": 0, "isOverTaking": 0, "isTurningAround": 0, "currentLanenumber": -1, "currentLanedirection": 0, "speedLimitlowerLimit": 0, "speedLimitupperLimit": 1000, "honkingAllowed": 1, "crosswalkAhead": 200, "junctionAhead": 200, "stopSignAhead": 200, "signalAhead": 0, "stoplineAhead": 200, "streetLightOn": 0, "specialLocationAheadlocation": 0, "specialLocationAheadtype": 0, "trafficLightAheadcolor": 3, "trafficLightAheadblink": 0, "PriorityNPCAhead": 0, "PriorityPedsAhead": 0, "isTrafficJam": 0, "reach_destination": 1, "collision": 0, "NPCAheadAhead": 1000, "NPCAheadspeed": 0, "NearestNPCAhead": 129.03625099914413, "NearestNPCspeed": 0.0, "NPCOppositeAhead": 1000, "NPCOppositespeed": 0}, {"time": 0.288699754, "gear": 1, "engineOn": 1, "direction": 1, "manualIntervention": 0, "speed": 0.0, "acc": 0.0, "brake": 0.0, "isLaneChanging": 0, "isOverTaking": 0, "isTurningAround": 0, "currentLanenumber": -1, "currentLanedirection": 0, "speedLimitlowerLimit": 0, "speedLimitupperLimit": 1000, "honkingAllowed": 1, "crosswalkAhead": 200, "junctionAhead": 200, "stopSignAhead": 200, "signalAhead": 0, "stoplineAhead": 200, "streetLightOn": 0, "specialLocationAheadlocation": 0, "specialLocationAheadtype": 0, "trafficLightAheadcolor": 3, "trafficLightAheadblink": 0, "PriorityNPCAhead": 0, "PriorityPedsAhead": 0, "isTrafficJam": 0, "reach_destination": 1, "collision": 0, "NPCAheadAhead": 1000, "NPCAheadspeed": 0, "NearestNPCAhead": 129.03625099914413, "NearestNPCspeed": 0.0, "NPCOppositeAhead": 1000, "NPCOppositespeed": 0}, {"time": 0.308608882, "gear": 1, "engineOn": 1, "direction": 1, "manualIntervention": 0, "speed": 0.0, "acc": 0.0, "brake": 0.0, "isLaneChanging": 0, "isOverTaking": 0, "isTurningAround": 0, "currentLanenumber": -1, "currentLanedirection": 0, "speedLimitlowerLimit": 0, "speedLimitupperLimit": 1000, "honkingAllowed": 1, "crosswalkAhead": 200, "junctionAhead": 200, "stopSignAhead": 200, "signalAhead": 0, "stoplineAhead": 200, "streetLightOn": 0, "specialLocationAheadlocation": 0, "specialLocationAheadtype": 0, "trafficLightAheadcolor": 3, "trafficLightAheadblink": 0, "PriorityNPCAhead": 0, "PriorityPedsAhead": 0, "isTrafficJam": 0, "reach_destination": 1, "collision": 0, "NPCAheadAhead": 1000, "NPCAheadspeed": 0, "NearestNPCAhead": 129.03625099914413, "NearestNPCspeed": 0.0, "NPCOppositeAhead": 1000, "NPCOppositespeed": 0}, {"time": 0.318745067, "gear": 1, "engineOn": 1, "direction": 1, "manualIntervention": 0, "speed": 0.0, "acc": 0.0, "brake": 0.0, "isLaneChanging": 0, "isOverTaking": 0, "isTurningAround": 0, "currentLanenumber": -1, "currentLanedirection": 0, "speedLimitlowerLimit": 0, "speedLimitupperLimit": 1000, "honkingAllowed": 1, "crosswalkAhead": 200, "junctionAhead": 200, "stopSignAhead": 200, "signalAhead": 0, "stoplineAhead": 200, "streetLightOn": 0, "specialLocationAheadlocation": 0, "specialLocationAheadtype": 0, "trafficLightAheadcolor": 3, "trafficLightAheadblink": 0, "PriorityNPCAhead": 0, "PriorityPedsAhead": 0, "isTrafficJam": 0, "reach_destination": 1, "collision": 0, "NPCAheadAhead": 1000, "NPCAheadspeed": 0, "NearestNPCAhead": 129.03625099914413, "NearestNPCspeed": 0.0, "NPCOppositeAhead": 1000, "NPCOppositespeed": 0}]}