{
  "folder": "log_raw_t71",
  "spec": {
    "kind": "F",
    "a": 0.0,
    "b": 5.0,
    "theta": 0.9,
    "predicate": {
      "unsafe": "1"
    }
  },
  "baseline": {
    "baseline_total_logs": 13,
    "baseline_satisfied": 0,
    "baseline_pct": 0.0
  },
  "optimized": {
    "optimized_prob": 0.026004565733836804,
    "initial_states": 13,
    "a_steps": 0,
    "b_steps": 5,
    "mc_trials": 1000,
    "mc_prob": 0.025,
    "mc_stderr": 0.0049371044145328745,
    "mc_ci95_low": 0.015323275347515567,
    "mc_ci95_high": 0.034676724652484434,
    "mc_vs_optimized_delta": -0.0010045657338368028
  },
  "proguard_offline": {
    "reach": {
      "unsafe_pct_before": 0.0,
      "unsafe_pct_after": 0.0,
      "completion_pct": 0.0
    },
    "law": {
      "prediction_pct": {
        "0.3": 0.0,
        "0.5": 0.0,
        "0.7": 0.0
      },
      "time_ahead_s": {
        "0.3": 0.0,
        "0.5": 0.0,
        "0.7": 0.0
      }
    }
  }
}